galaxy_job_config_init-0.1.2.dist-info/licenses/LICENSE
gxjobconfinit/__init__.py
gxjobconfinit/arg_parsing.py
gxjobconfinit/container_volumes.py
gxjobconfinit/generate.py
gxjobconfinit/py.typed
gxjobconfinit/script.py
gxjobconfinit/script_summary.py
gxjobconfinit/templates.py
gxjobconfinit/types.py
galaxy_job_config_init-0.1.2.dist-info/METADATA
galaxy_job_config_init-0.1.2.dist-info/WHEEL
galaxy_job_config_init-0.1.2.dist-info/entry_points.txt
galaxy_job_config_init-0.1.2.dist-info/top_level.txt
galaxy_job_config_init-0.1.2.dist-info/RECORD
